majel/__init__.py
majel/actions/__init__.py
majel/actions/base.py
majel/actions/browser/__init__.py
majel/actions/browser/handlers/__init__.py
majel/actions/browser/handlers/amazon.py
majel/actions/browser/handlers/base.py
majel/actions/browser/handlers/basic.py
majel/actions/browser/handlers/netflix.py
majel/actions/browser/handlers/selector.py
majel/actions/browser/handlers/youtube.py
majel/actions/browser/index.html
majel/actions/browser/template.html
majel/actions/kodi.py
majel/command.py
majel/config.py
majel/exceptions.py
majel/logger.py
majel/messages.py
majel-0.4.0.dist-info/entry_points.txt
majel-0.4.0.dist-info/LICENSE
majel-0.4.0.dist-info/WHEEL
majel-0.4.0.dist-info/METADATA
majel-0.4.0.dist-info/RECORD
