Metadata-Version: 2.1
Name: majel
Version: 0.4.0
Summary: A front-end for Mycroft that allows you to do cool things like stream video or surf the web.
Home-page: https://gitlab.com/danielquinn/majel
License: AGPL-3.0-or-later
Keywords: mycroft
Author: Daniel Quinn
Author-email: code@danielquinn.org
Requires-Python: >=3.8,<4.0
Classifier: Development Status :: 4 - Beta
Classifier: Intended Audience :: End Users/Desktop
Classifier: License :: OSI Approved :: GNU Affero General Public License v3 or later (AGPLv3+)
Classifier: Operating System :: POSIX :: Linux
Classifier: Programming Language :: Python :: 3
Classifier: Programming Language :: Python :: 3.8
Classifier: Programming Language :: Python :: 3.9
Classifier: Topic :: Internet :: WWW/HTTP :: Browsers
Classifier: Topic :: Multimedia
Requires-Dist: kodi-json (>=1.0.0,<2.0.0)
Requires-Dist: python-mpv (>=0.4.6,<0.5.0)
Requires-Dist: pyyaml (>=5.3.1,<6.0.0)
Requires-Dist: requests (>=2.23.0,<3.0.0)
Requires-Dist: selenium (>=3.141.0,<4.0.0)
Requires-Dist: websockets (>=8.1,<9.0)
Project-URL: Documentation, https://gitlab.com/danielquinn/majel
Project-URL: Repository, https://gitlab.com/danielquinn/majel
